[{"address": "\u4e0a\u6d77\u5e02\u4e0a\u6d77\u57ce\u533a\u9759\u5b89\u533a\u6210\u90fd\u5317\u8def199\u53f71204\u5ba4", "category": "\u7a7a\u6c14\u70b8\u9505", "ground": "PC,ABS,PMMA,LMPP,PBT,PS,POM,Si-PC,PMMA/ABS,MABS,PC/ABS,BPA", "money": 1000, "name": "\u5851\u79d1\u8d38\u6613\uff08\u4e0a\u6d77\uff09\u6709\u9650\u516c\u53f8", "property": ""}, {"address": "\u4e0a\u6d77\u5e02\u4e0a\u6d77\u57ce\u533a\u9759\u5b89\u533a\u4e07\u822a\u6e21\u8def", "category": "\u7a7a\u6c14\u70b8\u9505", "ground": "\u5851\u6599\u539f\u6599,PS,ABS,K\u80f6", "money": 500, "name": "\u4e0a\u6d77\u601d\u6cc9\u5546\u8d38\u6709\u9650\u516c\u53f8", "property": "\u5c0f\u5fae\u4f01\u4e1a"}, {"address": "\u4e0a\u6d77\u5e02\u4e0a\u6d77\u57ce\u533a\u9759\u5b89\u533a\u6c38\u5174\u8def258\u5f041\u53f71004\u5ba4", "category": "\u7a7a\u6c14\u70b8\u9505", "ground": "ABS,SAN,ASA", "money": 300, "name": "\u4e0a\u6d77\u5546\u8d3e\u5b9e\u4e1a\u6709\u9650\u516c\u53f8", "property": "\u5c0f\u5fae\u4f01\u4e1a"}, {"address": "\u4e0a\u6d77\u5e02\u4e0a\u6d77\u57ce\u533a\u9759\u5b89\u533a\u5317\u5b9d\u5174\u8def600\u53f7402\u5ba4", "category": "\u7a7a\u6c14\u70b8\u9505", "ground": "PC/ABS", "money": 200, "name": "\u4e0a\u6d77\u8d5b\u7136\u5b9e\u4e1a\u6709\u9650\u516c\u53f8", "property": "\u5c0f\u5fae\u4f01\u4e1a"}, {"address": "\u4e0a\u6d77\u5e02\u4e0a\u6d77\u57ce\u533a\u9759\u5b89\u533a\u6caa\u592a\u8def785\u53f722\u5e62429\u5ba4", "category": "\u7a7a\u6c14\u70b8\u9505", "ground": "pp,pe,pet,pa,pmma,pom,pc,abs", "money": 100, "name": "\u4e0a\u6d77\u53cb\u884c\u56fd\u9645\u8d38\u6613\u6709\u9650\u516c\u53f8", "property": "\u5c0f\u5fae\u4f01\u4e1a"}, {"address": "\u4e0a\u6d77\u5e02\u4e0a\u6d77\u57ce\u533a\u9759\u5b89\u533a\u95f8\u5317\u533a\u6caa\u592a\u652f\u8def", "category": "\u7a7a\u6c14\u70b8\u9505", "ground": "ABS\u677f\u6750", "money": 50, "name": "\u4e0a\u6d77\u857e\u5fb7\u5851\u80f6\u5236\u54c1\u5382", "property": "\u5c0f\u5fae\u4f01\u4e1a"}]